MANIFEST.in
setup.py
jarmodmoo/__init__.py
jarmodmoo/broker.py
jarmodmoo/client.py
jarmodmoo/config.py
jarmodmoo/defaults.cfg
jarmodmoo/helpers.py
jarmodmoo/protocol.py
jarmodmoo/tornado.py
jarmodmoo/worker.py
jarmodmoo.egg-info/PKG-INFO
jarmodmoo.egg-info/SOURCES.txt
jarmodmoo.egg-info/dependency_links.txt
jarmodmoo.egg-info/requires.txt
jarmodmoo.egg-info/top_level.txt