Metadata-Version: 1.0
Name: jarmodmoo
Version: 0.1.1
Summary: ØMQ Majordomo protocol
Home-page: https://github.com/pilt/jarmodmoo/
Author: Simon Pantzare
Author-email: simon+jarmodmoo@pewpewlabs.com
License: MIT
Platform: Posix; MacOS X; Windows
Classifier: Development Status :: 3 - Alpha
Classifier: Topic :: Internet
Classifier: Intended Audience :: Developers
Classifier: License :: OSI Approved :: MIT License
Classifier: Operating System :: OS Independent
Classifier: Programming Language :: Python :: 2
Classifier: Programming Language :: Python :: 2.7
